sidradataquality/__init__.py
sidradataquality/sdk/__init__.py
sidradataquality/sdk/constants.py
sidradataquality/sdk/utils.py
sidradataquality/sdk/api/__init__.py
sidradataquality/sdk/api/sidra/__init__.py
sidradataquality/sdk/api/sidra/core/__init__.py
sidradataquality/sdk/api/sidra/core/utils.py
sidradataquality/sdk/api/sidra/dataquality/__init__.py
sidradataquality/sdk/api/sidra/dataquality/utils.py
sidradataquality/sdk/data/__init__.py
sidradataquality/sdk/data/validationservice.py
sidradataquality/sdk/databricks/__init__.py
sidradataquality/sdk/databricks/databricksservice.py
sidradataquality/sdk/databricks/utils.py
sidradataquality/sdk/greatexpectations/__init__.py
sidradataquality/sdk/greatexpectations/contextservice.py
sidradataquality/sdk/log/__init__.py
sidradataquality/sdk/log/logging.py
sidradataquality/sdk/metadata/__init__.py
sidradataquality/sdk/metadata/assetservice.py
sidradataquality/sdk/metadata/dataintakeprocessservice.py
sidradataquality/sdk/metadata/entityservice.py
sidradataquality/sdk/metadata/providerservice.py
sidradataquality/sdk/metadata/validationservice.py
sidradataquality/sdk/report/__init__.py
sidradataquality/sdk/report/reportservice.py
sidradataquality/sdk/security/__init__.py
sidradataquality/sdk/security/auth.py
sidradataquality/sdk/settings/__init__.py
sidradataquality/sdk/settings/settingsservice.py
sidradataquality/sdk/storage/__init__.py
sidradataquality/sdk/storage/storageservice.py
sidradataquality-2025.8.3.dist-info/LICENSE
sidradataquality-2025.8.3.dist-info/METADATA
sidradataquality-2025.8.3.dist-info/WHEEL
sidradataquality-2025.8.3.dist-info/top_level.txt
sidradataquality-2025.8.3.dist-info/RECORD
