Metadata-Version: 2.1
Name: sidradataquality
Version: 2025.8.3
Summary: A SDK for Sidra data quality validations
Home-page: https://sidra.dev/
Author: Sidra Data Services
Author-email: info@sidra.dev
License: Copyright (C) Sidra Data Services - All Rights Reserved
License-File: LICENSE
Requires-Dist: SidraCoreApiPythonClient
Requires-Dist: SidraDataQualityApiPythonClient
Requires-Dist: great-expectations ==0.18.15
